django_restful_translator/__init__.py
django_restful_translator/admin.py
django_restful_translator/models.py
django_restful_translator/translation_providers.py
django_restful_translator/utils.py
django_restful_translator/drf/__init__.py
django_restful_translator/drf/fields.py
django_restful_translator/drf/serializers.py
django_restful_translator/management/__init__.py
django_restful_translator/management/commands/__init__.py
django_restful_translator/management/commands/drt_convert_locales.py
django_restful_translator/management/commands/drt_makemessages.py
django_restful_translator/management/commands/drt_translate_models.py
django_restful_translator/management/commands/drt_update_database.py
django_restful_translator/migrations/0001_initial.py
django_restful_translator/migrations/__init__.py
django_restful_translator-0.10.0.dist-info/LICENSE
django_restful_translator-0.10.0.dist-info/METADATA
django_restful_translator-0.10.0.dist-info/WHEEL
django_restful_translator-0.10.0.dist-info/top_level.txt
django_restful_translator-0.10.0.dist-info/RECORD
