Metadata-Version: 2.1
Name: django_restful_translator
Version: 0.10.0
Summary: A Django application providing translation functionalities for Django Rest Framework
Home-page: https://github.com/AlexIvanchyk/django_restful_translator
Author: Alex Ivanchyk
Author-email: alexander.ivanchik@gmail.com
License: MIT
Keywords: django rest-framework translation i18n
Classifier: Development Status :: 3 - Alpha
Classifier: Intended Audience :: Developers
Classifier: License :: OSI Approved :: MIT License
Classifier: Programming Language :: Python :: 3.9
Requires-Python: >=3.9
License-File: LICENSE
Requires-Dist: Django>=3.2
Requires-Dist: djangorestframework>=3.11
Requires-Dist: polib>=1.1
Requires-Dist: google-cloud-translate>=2.0.4
Requires-Dist: boto3>=1.26.31
Requires-Dist: deepl>=1.16.1
Provides-Extra: dev
Requires-Dist: pylint; extra == "dev"
Requires-Dist: black; extra == "dev"
Requires-Dist: mypy; extra == "dev"
Requires-Dist: coverage; extra == "dev"
